MANIFEST.in
README.md
__about__.py
setup.cfg
setup.py
magic_xxl/__init__.py
magic_xxl/audio.py
magic_xxl/elasticsearch_index.py
magic_xxl/redis_collection.py
magic_xxl/taskman.py
magic_xxl.egg-info/PKG-INFO
magic_xxl.egg-info/SOURCES.txt
magic_xxl.egg-info/dependency_links.txt
magic_xxl.egg-info/requires.txt
magic_xxl.egg-info/top_level.txt
magic_xxl/flask/__init__.py
magic_xxl/flask/newrelic_apm.py
magic_xxl/flask/rollbar_logger.py